Sequence_Detector_2.v
// Design and implement a sequence detector that meets the following specifications: 

//      The detector contains single input 'w' and output 'z'.  
//      All changes in the circuit occur on the positive edge of a clock signal. 
//      The output 'z' is equal to '1' only if input 'w' receives ‘’1’’ in 2 consecutive clock cycles. 
//      If the input remains 1 then output will remain 1

module Sequence_Detector_2(w, clk, z);

input w, clk;
output reg z;

reg [1:0] CS, NS;

initial begin
  CS = 2'b00;
  NS = 2'b00;
end

always @(posedge clk) begin
  CS <= NS;
end

always @(*) begin

  case (CS) 

    2'b00:begin
      if(w === 1) begin
        NS = 2'b01;
        z = 0;
      end
      else begin
        NS = 2'b00;
        z = 0;       
      end
    end

    2'b01:begin
      if(w === 1) begin
        NS = 2'b10;
        z = 0;
      end
      else begin
        NS = 2'b00;
        z = 0;       
      end      
    end

    2'b10:begin
      if(w === 1) begin
        NS = 2'b10;
        z = 1;
      end
      else begin
        NS = 2'b00;
        z = 0;       
      end      
    end
      
  endcase
end

endmodule

Sequence_Detector_2_tb.v
module Sequence_Detector_2_tb();

reg w, clk;
wire z;

Sequence_Detector_2 abc (
  .w(w), 
  .clk(clk), 
  .z(z)
);

initial begin
  $dumpfile("any name.vcd");
  $dumpvars(0);
end

initial begin
  clk = 0;
  w = 0;
  #20 w = 1;
  #10 w = 0;
  #20 w = 1;
  #10 w = 1;
  #10 w = 0;
  #10 w = 1;
  #10 w = 1;
  #10 w = 1;
  #10 w = 0;
  #1000 $finish();
end

always #5 clk = ~clk;


endmodule

any name.vcd
$date
	Mon Mar 17 02:44:19 2025
$end
$version
	Icarus Verilog
$end
$timescale
	1s
$end
$scope module Sequence_Detector_2_tb $end
$var wire 1 ! z $end
$var reg 1 " clk $end
$var reg 1 # w $end
$scope module abc $end
$var wire 1 " clk $end
$var wire 1 # w $end
$var reg 2 $ CS [1:0] $end
$var reg 2 % NS [1:0] $end
$var reg 1 ! z $end
$upscope $end
$upscope $end
$enddefinitions $end
$comment Show the parameter values. $end
$dumpall
$end
#0
$dumpvars
b0 %
b0 $
0#
0"
0!
$end
#5
1"
#10
0"
#15
1"
#20
b1 %
0"
1#
#25
b10 %
b1 $
1"
#30
b0 %
0"
0#
#35
b0 $
1"
#40
0"
#45
1"
#50
b1 %
0"
1#
#55
b10 %
b1 $
1"
#60
0"
#65
1!
b10 $
1"
#70
0!
b0 %
0"
0#
#75
b0 $
1"
#80
b1 %
0"
1#
#85
b10 %
b1 $
1"
#90
0"
#95
1!
b10 $
1"
#100
0"
#105
1"
#110
0!
b0 %
0"
0#
#115
b0 $
1"
